LICENSE.txt
MANIFEST.in
README.md
setup.cfg
setup.py
copyleaks/__init__.py
copyleaks/consts.py
copyleaks/copyleaks.py
copyleaks.egg-info/PKG-INFO
copyleaks.egg-info/SOURCES.txt
copyleaks.egg-info/dependency_links.txt
copyleaks.egg-info/requires.txt
copyleaks.egg-info/top_level.txt
copyleaks/clients/AiImageDetectionClient.py
copyleaks/clients/TextModerationClient.py
copyleaks/clients/__init__.py
copyleaks/clients/ai_detection_client.py
copyleaks/clients/writing_assistant_client.py
copyleaks/exceptions/__init__.py
copyleaks/exceptions/auth_expired_error.py
copyleaks/exceptions/command_error.py
copyleaks/exceptions/rate_limit_error.py
copyleaks/exceptions/under_maintenance_error.py
copyleaks/helpers/__init__.py
copyleaks/helpers/copyleaks_client_helper.py
copyleaks/models/__init__.py
copyleaks/models/delete.py
copyleaks/models/export.py
copyleaks/models/start.py
copyleaks/models/ImageDetection/Requests/CopyleaksAiImageDetectionRequestModel.py
copyleaks/models/ImageDetection/Responses/CopyleaksAiImageDetectionImageInfoModel.py
copyleaks/models/ImageDetection/Responses/CopyleaksAiImageDetectionResponseModel.py
copyleaks/models/ImageDetection/Responses/CopyleaksAiImageDetectionResultModel.py
copyleaks/models/ImageDetection/Responses/CopyleaksAiImageDetectionScannedDocumentModel.py
copyleaks/models/ImageDetection/Responses/CopyleaksAiImageDetectionSummaryModel.py
copyleaks/models/ImageDetection/Responses/CopyleaksImageMetadataModel.py
copyleaks/models/ImageDetection/Responses/CopyleaksImageShapeModel.py
copyleaks/models/TextModeration/Requests/CopyleaksTextModerationLabel.py
copyleaks/models/TextModeration/Requests/CopyleaksTextModerationRequestModel.py
copyleaks/models/TextModeration/Responses/CopyleaksTextModerationResponseModel.py
copyleaks/models/TextModeration/Responses/Submodules/ModerationsModel.py
copyleaks/models/TextModeration/Responses/Submodules/Text.py
copyleaks/models/TextModeration/Responses/Submodules/TextModerationChars.py
copyleaks/models/TextModeration/Responses/Submodules/TextModerationScannedDocument.py
copyleaks/models/TextModeration/Responses/Submodules/TextModerationsLegend.py
