Metadata-Version: 2.1
Name: copyleaks
Version: 5.1.0
Summary: Copyleaks API gives you access to a variety of plagiarism detection technologies to protect your online content. Get the most comprehensive plagiarism report for your content that is easy to use and integrate.
Home-page: https://api.copyleaks.com
Download-URL: https://github.com/Copyleaks/Python-Plagiarism-Checker
Author: Copyleaks ltd
Author-email: sales@copyleaks.com
Keywords: copyleaks,api,plagiarism,content,checker,online,academic,publishers,websites
License-File: LICENSE.txt
